<?xml version="1.0" encoding="UTF-8"?>
<templates xml:space="preserve">
    <!-- Delete when sign conversion is complete -->
    <t t-name="sign.type_buttons">
        <div class="o_sign_field_type_toolbar_title d-flex justify-content-center align-items-center">Fields</div>
        <div class="o_sign_field_type_toolbar_items d-flex flex-column">
            <t t-foreach="sign_item_types" t-as="item_type">
                <button type="button" class="o_sign_field_type_button btn btn-primary flex-shrink-0" t-att-data-item-type-id="item_type.id" title="Drag &amp; Drop a field in the PDF"><t t-esc="item_type.name"/></button>
            </t>
            <!-- When you mouse hover the last sign type button the button will be zoomed in a little
                 The following <br/> is added to prevent the horizontal overflow which will trigger a horizontal scrollbar. -->
            <br/>
        </div>
    </t>
</templates>
