<?xml version="1.0" encoding="utf-8"?>
<odoo>
    <record id="account_financial_report_executivesummary0" model="account.financial.html.report">
        <field name="name">Executive Summary</field>
        <field name="parent_id" ref="account.account_reports_legal_statements_menu"/>
        <field name="line_ids">
            <record id="account_financial_report_executivesummary_cash0" model="account.financial.html.report.line">
                <field name="name">Cash</field>
                <field name="sequence" eval="1"/>
                <field name="level" eval="0"/>
                <field name="children_ids">
                    <record id="account_financial_report_executivesummary_cash_received0" model="account.financial.html.report.line">
                        <field name="name">Cash received</field>
                        <field name="code">CR</field>
                        <field name="sequence" eval="1"/>
                        <field name="domain" eval="[('account_id.account_type', 'in', ('asset_cash', 'liability_credit_card')), ('debit', '&gt;', 0.0)]"/>
                        <field name="formulas">sum</field>
                        <field name="show_domain">never</field>
                        <field name="level" eval="3"/>
                        <field name="special_date_changer">strict_range</field>
                    </record>
                    <record id="account_financial_report_executivesummary_cash_spent0" model="account.financial.html.report.line">
                        <field name="name">Cash spent</field>
                        <field name="code">CS</field>
                        <field name="sequence" eval="2"/>
                        <field name="domain" eval="[('account_id.account_type', 'in', ('asset_cash', 'liability_credit_card')), ('credit', '&gt;', 0.0)]"/>
                        <field name="formulas">sum</field>
                        <field name="show_domain">never</field>
                        <field name="green_on_positive" eval="False"/>
                        <field name="level" eval="3"/>
                        <field name="special_date_changer">strict_range</field>
                    </record>
                    <record id="account_financial_report_executivesummary_cash_surplus0" model="account.financial.html.report.line">
                        <field name="name">Cash surplus</field>
                        <field name="sequence" eval="3"/>
                        <field name="formulas">CR + CS</field>
                        <field name="level" eval="3"/>
                    </record>
                    <record id="account_financial_report_executivesummary_closing_bank_balance0" model="account.financial.html.report.line">
                        <field name="name">Closing bank balance</field>
                        <field name="sequence" eval="4"/>
                        <field name="domain" eval="[('account_id.account_type', 'in', ('asset_cash', 'liability_credit_card'))]"/>
                        <field name="formulas">sum</field>
                        <field name="level" eval="3"/>
                    </record>
                </field>
            </record>
            <record id="account_financial_report_executivesummary_profitability0" model="account.financial.html.report.line">
                <field name="name">Profitability</field>
                <field name="sequence" eval="2"/>
                <field name="level" eval="0"/>
                <field name="children_ids">
                    <record id="account_financial_report_executivesummary_income0" model="account.financial.html.report.line">
                        <field name="name">Income</field>
                        <field name="sequence" eval="1"/>
                        <field name="formulas">INC</field>
                        <field name="level" eval="3"/>
                    </record>
                    <record id="account_financial_report_executivesummary_direct_costs0" model="account.financial.html.report.line">
                        <field name="name">Cost of Revenue</field>
                        <field name="sequence" eval="2"/>
                        <field name="formulas">COS</field>
                        <field name="green_on_positive" eval="False"/>
                        <field name="level" eval="3"/>
                    </record>
                    <record id="account_financial_report_executivesummary_gross_profit0" model="account.financial.html.report.line">
                        <field name="name">Gross profit</field>
                        <field name="sequence" eval="3"/>
                        <field name="formulas">GRP</field>
                        <field name="level" eval="3"/>
                    </record>
                    <record id="account_financial_report_executivesummary_expenses0" model="account.financial.html.report.line">
                        <field name="name">Expenses</field>
                        <field name="sequence" eval="4"/>
                        <field name="formulas">LEX</field>
                        <field name="green_on_positive" eval="False"/>
                        <field name="level" eval="3"/>
                    </record>
                    <record id="account_financial_report_executivesummary_profit0" model="account.financial.html.report.line">
                        <field name="name">Net Profit</field>
                        <field name="sequence" eval="5"/>
                        <field name="formulas">NEP</field>
                        <field name="level" eval="3"/>
                    </record>
                </field>
            </record>
            <record id="account_financial_report_executivesummary_balancesheet0" model="account.financial.html.report.line">
                <field name="name">Balance Sheet</field>
                <field name="sequence" eval="3"/>
                <field name="level" eval="0"/>
                <field name="children_ids">
                    <record id="account_financial_report_executivesummary_debtors0" model="account.financial.html.report.line">
                        <field name="name">Receivables</field>
                        <field name="code">DEB</field>
                        <field name="sequence" eval="1"/>
                        <field name="domain" eval="[('account_id.account_type', '=', 'asset_receivable')]"/>
                        <field name="formulas">sum</field>
                        <field name="show_domain">never</field>
                        <field name="level" eval="3"/>
                    </record>
                    <record id="account_financial_report_executivesummary_creditors0" model="account.financial.html.report.line">
                        <field name="name">Payables</field>
                        <field name="code">CRE</field>
                        <field name="sequence" eval="2"/>
                        <field name="domain" eval="[('account_id.account_type', '=', 'liability_payable')]"/>
                        <field name="formulas">sum</field>
                        <field name="show_domain">never</field>
                        <field name="green_on_positive" eval="False"/>
                        <field name="level" eval="3"/>
                    </record>
                    <record id="account_financial_report_executivesummary_net_assets0" model="account.financial.html.report.line">
                        <field name="name">Net assets</field>
                        <field name="sequence" eval="3"/>
                        <field name="formulas">NA</field>
                        <field name="level" eval="3"/>
                    </record>
                </field>
            </record>
            <record id="account_financial_report_executivesummary_performance0" model="account.financial.html.report.line">
                <field name="name">Performance</field>
                <field name="sequence" eval="4"/>
                <field name="level" eval="0"/>
                <field name="children_ids">
                    <record id="account_financial_report_executivesummary_gpmargin0" model="account.financial.html.report.line">
                        <field name="name">Gross profit margin (gross profit / operating income)</field>
                        <field name="sequence" eval="1"/>
                        <field name="formulas">GRP / OPINC</field>
                        <field name="figure_type">percents</field>
                        <field name="level" eval="3"/>
                    </record>
                    <record id="account_financial_report_executivesummary_npmargin0" model="account.financial.html.report.line">
                        <field name="name">Net profit margin (net profit / income)</field>
                        <field name="sequence" eval="2"/>
                        <field name="formulas">NEP / INC</field>
                        <field name="figure_type">percents</field>
                        <field name="level" eval="3"/>
                    </record>
                    <record id="account_financial_report_executivesummary_return_investment0" model="account.financial.html.report.line">
                        <field name="name">Return on investments (net profit / assets)</field>
                        <field name="sequence" eval="3"/>
                        <field name="formulas">NEP / TA</field>
                        <field name="figure_type">percents</field>
                        <field name="level" eval="3"/>
                    </record>
                </field>
            </record>
            <record id="account_financial_report_executivesummary_position0" model="account.financial.html.report.line">
                <field name="name">Position</field>
                <field name="sequence" eval="5"/>
                <field name="level" eval="0"/>
                <field name="children_ids">
                    <record id="account_financial_report_executivesummary_avdebt0" model="account.financial.html.report.line">
                        <field name="name">Average debtors days</field>
                        <field name="sequence" eval="1"/>
                        <field name="formulas">DEB / OPINC * NDays</field>
                        <field name="figure_type">no_unit</field>
                        <field name="green_on_positive" eval="False"/>
                        <field name="level" eval="3"/>
                    </record>
                    <record id="account_financial_report_executivesummary_avgcre0" model="account.financial.html.report.line">
                        <field name="name">Average creditors days</field>
                        <field name="sequence" eval="2"/>
                        <field name="formulas">-CRE / OPINC * NDays</field>
                        <field name="figure_type">no_unit</field>
                        <field name="green_on_positive" eval="False"/>
                        <field name="level" eval="3"/>
                    </record>
                    <record id="account_financial_report_executivesummary_st_cash_forecast0" model="account.financial.html.report.line">
                        <field name="name">Short term cash forecast</field>
                        <field name="sequence" eval="3"/>
                        <field name="formulas">DEB + CRE</field>
                        <field name="level" eval="3"/>
                    </record>
                    <record id="account_financial_report_executivesummary_ca_to_l0" model="account.financial.html.report.line">
                        <field name="name">Current assets to liabilities</field>
                        <field name="sequence" eval="4"/>
                        <field name="formulas">CA / CL</field>
                        <field name="figure_type">no_unit</field>
                        <field name="level" eval="3"/>
                    </record>
                </field>
            </record>
        </field>
    </record>
</odoo>
